{
  "metadata" : {
    "screener_company_id" : "6314",
    "company_code" : "HNDFDS",
    "company_name" : "Hindustan Foods",
    "screener_company_link" : "https://www.screener.in/company/HNDFDS",
    "screener_price_history_link" : "https://www.screener.in/api/company/6314/chart/?q=Price-DMA50-DMA200-Volume&days=365",
    "screener_quarterly_results_link" : "https://www.screener.in/api/company/6314/chart/?q=GPM-OPM-NPM-Quarter+Sales&days=10000"
  },
  "detail" : {
    "company_code" : "HNDFDS",
    "company_name" : "Hindustan Foods",
    "market_cap" : "₹ 6,501 Cr.",
    "pe_ratio" : "54.9",
    "description" : "Hindustan Foods Limited is an India-based company, which is engaged in contract manufacturing of various FMCG products including food, home care, personal care, beverages etc. They also do manufacturing of leather shoes and accessories"
  },
  "technical_history" : [ ]
}